<?xml version="1.0" encoding="UTF-8"?>
<java version="1.8.0_131" class="java.beans.XMLDecoder">
 <object class="trabajofinal.Controlador" id="Controlador0">
  <void property="alumnos">
   <void method="put">
    <string>ALU0000</string>
    <object class="trabajofinal.Alumno" id="Alumno0">
     <void property="apellido">
      <string>Lanzillotta</string>
     </void>
     <void property="domicilio">
      <object class="trabajofinal.Domicilio">
       <void property="calle">
        <string>Chubut</string>
       </void>
       <void property="numero">
        <int>1953</int>
       </void>
      </object>
     </void>
     <void property="email">
      <string>franco@lanzi</string>
     </void>
     <void property="historia">
      <object class="trabajofinal.ObserverTreeMap" id="ObserverTreeMap0">
       <void property="coleccion">
        <void method="put">
         <string>ASI0000</string>
         <object class="trabajofinal.Asignatura" id="Asignatura0">
          <void property="correlativas">
           <object class="trabajofinal.ObserverTreeMap"/>
          </void>
          <void property="identificacion">
           <string>ASI0000</string>
          </void>
          <void property="nombre">
           <string>Matematica</string>
          </void>
         </object>
        </void>
        <void method="put">
         <string>ASI0001</string>
         <object class="trabajofinal.Asignatura" id="Asignatura1">
          <void property="correlativas">
           <object class="trabajofinal.ObserverTreeMap"/>
          </void>
          <void property="identificacion">
           <string>ASI0001</string>
          </void>
          <void property="nombre">
           <string>Quimica</string>
          </void>
         </object>
        </void>
       </void>
      </object>
     </void>
     <void property="legajo">
      <string>ALU0000</string>
     </void>
     <void property="nombre">
      <string>Franco</string>
     </void>
    </object>
   </void>
   <void method="put">
    <string>ALU0001</string>
    <object class="trabajofinal.Alumno" id="Alumno1">
     <void property="apellido">
      <string>Vilchez</string>
     </void>
     <void property="domicilio">
      <object class="trabajofinal.Domicilio">
       <void property="calle">
        <string>Alguna</string>
       </void>
       <void property="numero">
        <int>1234</int>
       </void>
      </object>
     </void>
     <void property="email">
      <string>sol@vilchez</string>
     </void>
     <void property="historia">
      <object class="trabajofinal.ObserverTreeMap"/>
     </void>
     <void property="legajo">
      <string>ALU0001</string>
     </void>
     <void property="nombre">
      <string>Sol</string>
     </void>
    </object>
   </void>
   <void method="put">
    <string>ALU0002</string>
    <object class="trabajofinal.Alumno" id="Alumno2">
     <void property="apellido">
      <string>Pablos</string>
     </void>
     <void property="domicilio">
      <object class="trabajofinal.Domicilio">
       <void property="calle">
        <string>Chaco</string>
       </void>
       <void property="numero">
        <int>50</int>
       </void>
      </object>
     </void>
     <void property="email">
      <string>braulio@pablos</string>
     </void>
     <void property="historia">
      <object class="trabajofinal.ObserverTreeMap"/>
     </void>
     <void property="legajo">
      <string>ALU0002</string>
     </void>
     <void property="nombre">
      <string>Braulio</string>
     </void>
    </object>
   </void>
   <void method="put">
    <string>ALU0003</string>
    <object class="trabajofinal.Alumno" id="Alumno3">
     <void property="apellido">
      <string>Mateos</string>
     </void>
     <void property="domicilio">
      <object class="trabajofinal.Domicilio">
       <void property="calle">
        <string>Independencia</string>
       </void>
       <void property="numero">
        <int>4300</int>
       </void>
      </object>
     </void>
     <void property="email">
      <string>wen@mateos</string>
     </void>
     <void property="historia">
      <object class="trabajofinal.ObserverTreeMap"/>
     </void>
     <void property="legajo">
      <string>ALU0003</string>
     </void>
     <void property="nombre">
      <string>Wenceslao</string>
     </void>
    </object>
   </void>
  </void>
  <void property="asignaturas">
   <void method="put">
    <string>ASI0000</string>
    <object idref="Asignatura0"/>
   </void>
   <void method="put">
    <string>ASI0001</string>
    <object idref="Asignatura1"/>
   </void>
   <void method="put">
    <string>ASI0002</string>
    <object class="trabajofinal.Asignatura" id="Asignatura2">
     <void property="correlativas">
      <object class="trabajofinal.ObserverTreeMap" id="ObserverTreeMap1">
       <void property="coleccion">
        <void method="put">
         <string>ASI0000</string>
         <object idref="Asignatura0"/>
        </void>
        <void method="put">
         <string>ASI0001</string>
         <object idref="Asignatura1"/>
        </void>
       </void>
      </object>
     </void>
     <void property="identificacion">
      <string>ASI0002</string>
     </void>
     <void property="nombre">
      <string>Fisica</string>
     </void>
    </object>
   </void>
   <void method="put">
    <string>ASI0003</string>
    <object class="trabajofinal.Asignatura" id="Asignatura3">
     <void property="correlativas">
      <object class="trabajofinal.ObserverTreeMap" id="ObserverTreeMap2">
       <void property="coleccion">
        <void method="put">
         <string>ASI0000</string>
         <object idref="Asignatura0"/>
        </void>
       </void>
      </object>
     </void>
     <void property="identificacion">
      <string>ASI0003</string>
     </void>
     <void property="nombre">
      <string>Programacion</string>
     </void>
    </object>
   </void>
   <void method="put">
    <string>ASI0004</string>
    <object class="trabajofinal.Asignatura">
     <void property="correlativas">
      <object class="trabajofinal.ObserverTreeMap" id="ObserverTreeMap3">
       <void property="coleccion">
        <void method="put">
         <string>ASI0000</string>
         <object idref="Asignatura0"/>
        </void>
        <void method="put">
         <string>ASI0003</string>
         <object idref="Asignatura3"/>
        </void>
       </void>
      </object>
     </void>
     <void property="identificacion">
      <string>ASI0004</string>
     </void>
     <void property="nombre">
      <string>Analisis</string>
     </void>
    </object>
   </void>
   <void method="put">
    <string>ASI0005</string>
    <object class="trabajofinal.Asignatura" id="Asignatura4">
     <void property="correlativas">
      <object class="trabajofinal.ObserverTreeMap" id="ObserverTreeMap4">
       <void property="coleccion">
        <void method="put">
         <string>ASI0002</string>
         <object idref="Asignatura2"/>
        </void>
        <void method="put">
         <string>ASI0003</string>
         <object idref="Asignatura3"/>
        </void>
       </void>
      </object>
     </void>
     <void property="identificacion">
      <string>ASI0005</string>
     </void>
     <void property="nombre">
      <string>Arquitectura</string>
     </void>
    </object>
   </void>
   <void method="put">
    <string>ASI0006</string>
    <object class="trabajofinal.Asignatura" id="Asignatura5">
     <void property="correlativas">
      <object class="trabajofinal.ObserverTreeMap" id="ObserverTreeMap5">
       <void property="coleccion">
        <void method="put">
         <string>ASI0000</string>
         <object idref="Asignatura0"/>
        </void>
       </void>
      </object>
     </void>
     <void property="identificacion">
      <string>ASI0006</string>
     </void>
     <void property="nombre">
      <string>Estadistica</string>
     </void>
    </object>
   </void>
   <void method="put">
    <string>ASI0007</string>
    <object class="trabajofinal.Asignatura">
     <void property="correlativas">
      <object class="trabajofinal.ObserverTreeMap" id="ObserverTreeMap6">
       <void property="coleccion">
        <void method="put">
         <string>ASI0005</string>
         <object idref="Asignatura4"/>
        </void>
        <void method="put">
         <string>ASI0006</string>
         <object idref="Asignatura5"/>
        </void>
       </void>
      </object>
     </void>
     <void property="identificacion">
      <string>ASI0007</string>
     </void>
     <void property="nombre">
      <string>Teoria de la Informacion</string>
     </void>
    </object>
   </void>
  </void>
  <void property="cursadas">
   <void method="put">
    <string>CUR0000</string>
    <object class="trabajofinal.Cursada">
     <void property="alumnos">
      <object class="trabajofinal.ObserverTreeMap" id="ObserverTreeMap7">
       <void property="coleccion">
        <void method="put">
         <string>ALU0001</string>
         <object idref="Alumno1"/>
        </void>
        <void method="put">
         <string>ALU0002</string>
         <object idref="Alumno2"/>
        </void>
        <void method="put">
         <string>ALU0003</string>
         <object idref="Alumno3"/>
        </void>
       </void>
      </object>
     </void>
     <void property="asignatura">
      <object idref="Asignatura0"/>
     </void>
     <void property="dia">
      <string>Viernes</string>
     </void>
     <void property="horaFin">
      <string>14:00</string>
     </void>
     <void property="horaInicio">
      <string>12:00</string>
     </void>
     <void property="identificacion">
      <string>CUR0000</string>
     </void>
     <void property="periodo">
      <string>01-1996</string>
     </void>
     <void property="profesores">
      <object class="trabajofinal.ObserverTreeMap"/>
     </void>
    </object>
   </void>
   <void method="put">
    <string>CUR0001</string>
    <object class="trabajofinal.Cursada">
     <void property="alumnos">
      <object class="trabajofinal.ObserverTreeMap" id="ObserverTreeMap8">
       <void property="coleccion">
        <void method="put">
         <string>ALU0001</string>
         <object idref="Alumno1"/>
        </void>
       </void>
      </object>
     </void>
     <void property="asignatura">
      <object idref="Asignatura1"/>
     </void>
     <void property="dia">
      <string>Viernes</string>
     </void>
     <void property="horaFin">
      <string>10:00</string>
     </void>
     <void property="horaInicio">
      <string>08:00</string>
     </void>
     <void property="identificacion">
      <string>CUR0001</string>
     </void>
     <void property="periodo">
      <string>02-1994</string>
     </void>
     <void property="profesores">
      <object class="trabajofinal.ObserverTreeMap"/>
     </void>
    </object>
   </void>
   <void method="put">
    <string>CUR0002</string>
    <object class="trabajofinal.Cursada">
     <void property="alumnos">
      <object class="trabajofinal.ObserverTreeMap" id="ObserverTreeMap9">
       <void property="coleccion">
        <void method="put">
         <string>ALU0000</string>
         <object idref="Alumno0"/>
        </void>
       </void>
      </object>
     </void>
     <void property="asignatura">
      <object idref="Asignatura2"/>
     </void>
     <void property="dia">
      <string>Viernes</string>
     </void>
     <void property="horaFin">
      <string>20:00</string>
     </void>
     <void property="horaInicio">
      <string>18:00</string>
     </void>
     <void property="identificacion">
      <string>CUR0002</string>
     </void>
     <void property="periodo">
      <string>01-2008</string>
     </void>
     <void property="profesores">
      <object class="trabajofinal.ObserverTreeMap"/>
     </void>
    </object>
   </void>
   <void method="put">
    <string>CUR0004</string>
    <object class="trabajofinal.Cursada">
     <void property="alumnos">
      <object class="trabajofinal.ObserverTreeMap"/>
     </void>
     <void property="asignatura">
      <object idref="Asignatura4"/>
     </void>
     <void property="dia">
      <string>Viernes</string>
     </void>
     <void property="horaFin">
      <string>17:30</string>
     </void>
     <void property="horaInicio">
      <string>15:30</string>
     </void>
     <void property="identificacion">
      <string>CUR0004</string>
     </void>
     <void property="periodo">
      <string>01-2013</string>
     </void>
     <void property="profesores">
      <object class="trabajofinal.ObserverTreeMap"/>
     </void>
    </object>
   </void>
   <void method="put">
    <string>CUR0005</string>
    <object class="trabajofinal.Cursada">
     <void property="alumnos">
      <object class="trabajofinal.ObserverTreeMap" id="ObserverTreeMap10">
       <void property="coleccion">
        <void method="put">
         <string>ALU0000</string>
         <object idref="Alumno0"/>
        </void>
       </void>
      </object>
     </void>
     <void property="asignatura">
      <object idref="Asignatura2"/>
     </void>
     <void property="dia">
      <string>Martes</string>
     </void>
     <void property="horaFin">
      <string>10:00</string>
     </void>
     <void property="horaInicio">
      <string>08:00</string>
     </void>
     <void property="identificacion">
      <string>CUR0005</string>
     </void>
     <void property="periodo">
      <string>02-2017</string>
     </void>
     <void property="profesores">
      <object class="trabajofinal.ObserverTreeMap" id="ObserverTreeMap11">
       <void property="coleccion">
        <void method="put">
         <string>PRO0000</string>
         <object class="trabajofinal.Profesor" id="Profesor0">
          <void property="apellido">
           <string>Viau</string>
          </void>
          <void property="competencias">
           <object class="trabajofinal.ObserverTreeMap" id="ObserverTreeMap12">
            <void property="coleccion">
             <void method="put">
              <string>ASI0000</string>
              <object idref="Asignatura0"/>
             </void>
             <void method="put">
              <string>ASI0002</string>
              <object idref="Asignatura2"/>
             </void>
            </void>
           </object>
          </void>
          <void property="domicilio">
           <object class="trabajofinal.Domicilio">
            <void property="calle">
             <string>Alguna</string>
            </void>
            <void property="numero">
             <int>1234</int>
            </void>
           </object>
          </void>
          <void property="email">
           <string>javier@viau</string>
          </void>
          <void property="legajo">
           <string>PRO0000</string>
          </void>
          <void property="nombre">
           <string>Javier</string>
          </void>
          <void property="telefono">
           <string>12345678</string>
          </void>
         </object>
        </void>
       </void>
      </object>
     </void>
    </object>
   </void>
   <void method="put">
    <string>CUR0006</string>
    <object class="trabajofinal.Cursada">
     <void property="alumnos">
      <object class="trabajofinal.ObserverTreeMap"/>
     </void>
     <void property="asignatura">
      <object idref="Asignatura2"/>
     </void>
     <void property="dia">
      <string>Martes</string>
     </void>
     <void property="horaFin">
      <string>10:00</string>
     </void>
     <void property="horaInicio">
      <string>08:00</string>
     </void>
     <void property="identificacion">
      <string>CUR0006</string>
     </void>
     <void property="periodo">
      <string>02-2017</string>
     </void>
     <void property="profesores">
      <object class="trabajofinal.ObserverTreeMap"/>
     </void>
    </object>
   </void>
  </void>
  <void property="profesores">
   <void method="put">
    <string>PRO0000</string>
    <object idref="Profesor0"/>
   </void>
  </void>
 </object>
 <int>4</int>
 <int>8</int>
 <object idref="Controlador0"/>
 <int>7</int>
 <int>1</int>
</java>
